talk2db/__init__.py
talk2db/cli.py
talk2db/core.py
talk2db-0.1.0.dist-info/METADATA
talk2db-0.1.0.dist-info/WHEEL
talk2db-0.1.0.dist-info/entry_points.txt
talk2db-0.1.0.dist-info/top_level.txt
talk2db-0.1.0.dist-info/RECORD
