Metadata-Version: 2.4
Name: talk2db
Version: 0.1.0
Summary: Natural Language Query Interface for CQL and SQL
Home-page: https://github.com/Akash-Gunasekar/talk2db
Author: Akash Gunasekar
Author-email: akashpersonal18@gmail.com
Keywords: natural language processing,sql,cypher,database,query,nlp
Dynamic: author
Dynamic: author-email
Dynamic: description
Dynamic: description-content-type
Dynamic: home-page
Dynamic: keywords
Dynamic: summary
